klu/__init__.py
klu/action/__init__.py
klu/action/client.py
klu/action/constants.py
klu/action/errors.py
klu/action/models.py
klu/api/__init__.py
klu/api/client.py
klu/api/config.py
klu/api/constants.py
klu/api/sse_client.py
klu/application/__init__.py
klu/application/client.py
klu/application/constants.py
klu/application/errors.py
klu/application/models.py
klu/client/__init__.py
klu/client/klu.py
klu/common/__init__.py
klu/common/client.py
klu/common/errors.py
klu/common/models.py
klu/data/__init__.py
klu/data/client.py
klu/data/constants.py
klu/data/errors.py
klu/data/models.py
klu/data_index/__init__.py
klu/data_index/client.py
klu/data_index/constants.py
klu/data_index/errors.py
klu/data_index/models.py
klu/klu.py
klu/model/__init__.py
klu/model/client.py
klu/model/constants.py
klu/model/errors.py
klu/model/models.py
klu/session/__init__.py
klu/session/client.py
klu/session/constants.py
klu/session/models.py
klu/utils/dict_helpers.py
klu/utils/file_upload.py
klu/utils/paginator.py
klu/workspace/__init__.py
klu/workspace/client.py
klu/workspace/constants.py
klu/workspace/errors.py
klu/workspace/models.py
klu_test_pipeline-0.1.6.dist-info/LICENSE
klu_test_pipeline-0.1.6.dist-info/METADATA
klu_test_pipeline-0.1.6.dist-info/WHEEL
klu_test_pipeline-0.1.6.dist-info/RECORD
