Metadata-Version: 2.1
Name: klu-test-pipeline
Version: 0.1.6
Summary: SDK for building AI Enabled apps.
Home-page: https://github.com/ssabev/klu
License: MIT
Author: Stefan Sabev
Author-email: stefan@klu.ai
Requires-Python: >=3.7,<4.0
Classifier: Development Status :: 2 - Pre-Alpha
Classifier: Intended Audience :: Developers
Classifier: License :: OSI Approved :: MIT License
Classifier: Natural Language :: English
Classifier: Programming Language :: Python :: 3
Classifier: Programming Language :: Python :: 3.7
Classifier: Programming Language :: Python :: 3.8
Classifier: Programming Language :: Python :: 3.9
Classifier: Programming Language :: Python :: 3.10
Classifier: Programming Language :: Python :: 3.11
Requires-Dist: aiofiles (==23.1.0)
Requires-Dist: aiohttp (==3.8.4)
Requires-Dist: aiohttp-sse-client (==0.2.1)
